scribe_cli/__init__.py
scribe_cli/llm_infer.py
scribe_cli/open_gui.py
scribe_cli/prompt_gen.py
scribe_cli/scribe.py
scribe_ai-0.0.1.dist-info/METADATA
scribe_ai-0.0.1.dist-info/WHEEL
scribe_ai-0.0.1.dist-info/entry_points.txt
scribe_ai-0.0.1.dist-info/top_level.txt
scribe_ai-0.0.1.dist-info/RECORD
