Metadata-Version: 2.1
Name: scribe-ai
Version: 0.0.1
Summary: scribe is an AI coding assistant, it allows an LLM to talk to your codebase directly from your terminal
Home-page: UNKNOWN
Author: Ansh Chadha
Author-email: anshchadha9211@gmail.com
License: UNKNOWN
Platform: UNKNOWN
Requires-Dist: click==8.1.7
Requires-Dist: anthropic==0.34.2
